<markers>
<marker lat="49.72316" long="8.25415" descriz="73368"/>
<marker lat="49.70566" long="8.27981" descriz="73368"/>
<marker lat="50.11882" long="8.69049" descriz="73368"/>
<marker lat="49.63796" long="8.21793" descriz="111159"/>
<marker lat="49.68874" long="8.12767" descriz="59102"/>
<marker lat="49.81" long="8.35273" descriz="63062"/>
<marker lat="49.90799" long="8.20128" descriz="42598"/>
<marker lat="49.7928" long="8.53882" descriz="127647"/>
<marker lat="49.66437" long="8.797" descriz="171489"/>
<marker lat="49.90439" long="8.19037" descriz="115057"/>
<marker lat="49.88496" long="8.62822" descriz="195450"/>
<marker lat="49.91477" long="8.11608" descriz="50480"/>
<marker lat="50.10721" long="8.68774" descriz="171279"/>
<marker lat="49.71016" long="8.60738" descriz="143451"/>
<marker lat="49.65591" long="7.9027" descriz="154316"/>
<marker lat="49.95736" long="8.20309" descriz="304"/>
<marker lat="49.58218" long="8.35508" descriz="118261"/>
<marker lat="50.00875" long="8.31299" descriz="76891"/>
<marker lat="49.88863" long="8.52586" descriz="103977"/>
<marker lat="49.67628" long="8.62729" descriz="26278"/>
<marker lat="49.801" long="8.63906" descriz="89378"/>
<marker lat="49.48852" long="8.17709" descriz="166236"/>
<marker lat="49.81778" long="8.64434" descriz="165415"/>
<marker lat="50.02568" long="8.39351" descriz="12441"/>
<marker lat="49.59401" long="7.98055" descriz="152099"/>
<marker lat="49.99677" long="8.68033" descriz="50427"/>
</markers>
