<markers>
<marker lat="50.11376" long="8.68708" descriz="103434"/>
<marker lat="50.11381" long="8.6923" descriz="103434"/>
<marker lat="50.11368" long="8.6743" descriz="103434"/>
<marker lat="50.11376" long="8.68708" descriz="193415"/>
<marker lat="50.1142" long="8.67094" descriz="75199"/>
<marker lat="50.11913" long="8.69078" descriz="93515"/>
<marker lat="50.10692" long="8.69225" descriz="127855"/>
<marker lat="50.10405" long="8.69021" descriz="106309"/>
<marker lat="50.1099" long="8.67964" descriz="15851"/>
<marker lat="50.11281" long="8.68116" descriz="80695"/>
<marker lat="50.10715" long="8.6895" descriz="163400"/>
<marker lat="50.10657" long="8.68749" descriz="119639"/>
<marker lat="50.11738" long="8.692" descriz="140376"/>
<marker lat="50.11577" long="8.69549" descriz="152065"/>
<marker lat="50.11472" long="8.69217" descriz="69642"/>
<marker lat="50.11472" long="8.69217" descriz="96908"/>
<marker lat="50.11489" long="8.6922" descriz="138110"/>
<marker lat="50.11346" long="8.69059" descriz="168986"/>
<marker lat="50.1143" long="8.68987" descriz="186897"/>
<marker lat="50.11354" long="8.69028" descriz="74999"/>
<marker lat="50.11354" long="8.69028" descriz="93883"/>
<marker lat="50.11527" long="8.69259" descriz="67174"/>
<marker lat="50.11502" long="8.69331" descriz="130694"/>
<marker lat="50.11502" long="8.69331" descriz="173340"/>
<marker lat="50.11293" long="8.692" descriz="86317"/>
<marker lat="50.11559" long="8.69256" descriz="47484"/>
<marker lat="50.11329" long="8.69315" descriz="152724"/>
<marker lat="50.11306" long="8.69297" descriz="5599"/>
<marker lat="50.11306" long="8.69297" descriz="159776"/>
<marker lat="50.11306" long="8.69297" descriz="171173"/>
<marker lat="50.11363" long="8.68918" descriz="72658"/>
<marker lat="50.11561" long="8.68933" descriz="121692"/>
<marker lat="50.11272" long="8.68958" descriz="104129"/>
<marker lat="50.11272" long="8.68958" descriz="121162"/>
<marker lat="50.11405" long="8.69481" descriz="128536"/>
<marker lat="50.1138" long="8.69481" descriz="14251"/>
<marker lat="50.11494" long="8.69483" descriz="160974"/>
<marker lat="50.11474" long="8.68789" descriz="191484"/>
<marker lat="50.11474" long="8.68789" descriz="160161"/>
<marker lat="50.11474" long="8.68789" descriz="197341"/>
<marker lat="50.11474" long="8.68789" descriz="141272"/>
<marker lat="50.11456" long="8.68774" descriz="43239"/>
<marker lat="50.11456" long="8.68774" descriz="80644"/>
<marker lat="50.11481" long="8.68772" descriz="171118"/>
<marker lat="50.11481" long="8.68772" descriz="89148"/>
<marker lat="50.11481" long="8.68772" descriz="15963"/>
<marker lat="50.11566" long="8.6878" descriz="128342"/>
<marker lat="50.11566" long="8.6878" descriz="33035"/>
<marker lat="50.11546" long="8.68751" descriz="157686"/>
<marker lat="50.11736" long="8.69109" descriz="151113"/>
<marker lat="50.11736" long="8.69109" descriz="45605"/>
<marker lat="50.11236" long="8.69534" descriz="147869"/>
<marker lat="50.112" long="8.68806" descriz="46671"/>
<marker lat="50.11253" long="8.68728" descriz="84772"/>
<marker lat="50.11346" long="8.69638" descriz="134773"/>
<marker lat="50.11457" long="8.68626" descriz="92068"/>
<marker lat="50.11457" long="8.68626" descriz="24951"/>
<marker lat="50.11171" long="8.68806" descriz="27351"/>
<marker lat="50.1111" long="8.6938" descriz="164208"/>
<marker lat="50.11557" long="8.68635" descriz="65067"/>
<marker lat="50.11697" long="8.68771" descriz="165072"/>
<marker lat="50.11697" long="8.68771" descriz="40025"/>
<marker lat="50.11697" long="8.68771" descriz="138860"/>
<marker lat="50.11122" long="8.6945" descriz="20750"/>
<marker lat="50.11739" long="8.68786" descriz="1406"/>
<marker lat="50.11831" long="8.69156" descriz="85822"/>
<marker lat="50.11243" long="8.68594" descriz="8887"/>
<marker lat="50.11243" long="8.68594" descriz="97516"/>
<marker lat="50.11706" long="8.68669" descriz="156952"/>
<marker lat="50.11782" long="8.68795" descriz="28469"/>
<marker lat="50.11782" long="8.68795" descriz="47068"/>
<marker lat="50.11348" long="8.685" descriz="110657"/>
<marker lat="50.11068" long="8.68797" descriz="117965"/>
<marker lat="50.1148" long="8.68484" descriz="124103"/>
<marker lat="50.11036" long="8.69416" descriz="731"/>
<marker lat="50.11084" long="8.69586" descriz="73286"/>
<marker lat="50.11031" long="8.68792" descriz="181852"/>
<marker lat="50.11031" long="8.68792" descriz="66681"/>
<marker lat="50.1096" long="8.69259" descriz="115030"/>
<marker lat="50.10961" long="8.69371" descriz="104487"/>
<marker lat="50.11344" long="8.68386" descriz="153707"/>
<marker lat="50.11218" long="8.68432" descriz="179904"/>
<marker lat="50.10927" long="8.69266" descriz="37467"/>
<marker lat="50.11417" long="8.68353" descriz="108329"/>
<marker lat="50.11417" long="8.68353" descriz="816"/>
<marker lat="50.11417" long="8.68353" descriz="42921"/>
<marker lat="50.11417" long="8.68353" descriz="62590"/>
<marker lat="50.11467" long="8.68353" descriz="99159"/>
<marker lat="50.10917" long="8.69303" descriz="105190"/>
<marker lat="50.10917" long="8.69303" descriz="190119"/>
<marker lat="50.10917" long="8.69303" descriz="125662"/>
<marker lat="50.10917" long="8.69303" descriz="139214"/>
<marker lat="50.10959" long="8.68781" descriz="103187"/>
<marker lat="50.10959" long="8.68781" descriz="195384"/>
<marker lat="50.10959" long="8.68781" descriz="181416"/>
<marker lat="50.10959" long="8.68774" descriz="172125"/>
<marker lat="50.10959" long="8.68768" descriz="181830"/>
<marker lat="50.10959" long="8.68768" descriz="29151"/>
<marker lat="50.10959" long="8.68768" descriz="95655"/>
<marker lat="50.10947" long="8.68772" descriz="115083"/>
<marker lat="50.10917" long="8.69431" descriz="151739"/>
<marker lat="50.10936" long="8.68795" descriz="120209"/>
<marker lat="50.11832" long="8.68561" descriz="140053"/>
<marker lat="50.1088" long="8.69165" descriz="154169"/>
<marker lat="50.10916" long="8.69471" descriz="122173"/>
<marker lat="50.10955" long="8.68692" descriz="30713"/>
<marker lat="50.11652" long="8.68342" descriz="157306"/>
<marker lat="50.10917" long="8.6961" descriz="103452"/>
<marker lat="50.10951" long="8.68595" descriz="115878"/>
<marker lat="50.10951" long="8.68595" descriz="147921"/>
<marker lat="50.11801" long="8.68413" descriz="100805"/>
<marker lat="50.11801" long="8.68413" descriz="97148"/>
<marker lat="50.10909" long="8.69633" descriz="154416"/>
<marker lat="50.10944" long="8.68519" descriz="69456"/>
<marker lat="50.11184" long="8.68225" descriz="63684"/>
<marker lat="50.11633" long="8.68178" descriz="163253"/>
<marker lat="50.11945" long="8.68502" descriz="178817"/>
<marker lat="50.11281" long="8.68116" descriz="47909"/>
<marker lat="50.11167" long="8.68165" descriz="50813"/>
<marker lat="50.11746" long="8.68187" descriz="42856"/>
<marker lat="50.11091" long="8.682" descriz="181559"/>
<marker lat="50.11371" long="8.68042" descriz="94206"/>
<marker lat="50.10717" long="8.69255" descriz="106890"/>
<marker lat="50.11403" long="8.68029" descriz="189178"/>
<marker lat="50.10746" long="8.68777" descriz="190307"/>
<marker lat="50.10691" long="8.69249" descriz="133357"/>
<marker lat="50.10689" long="8.69205" descriz="105673"/>
<marker lat="50.11959" long="8.68334" descriz="98557"/>
<marker lat="50.10721" long="8.68774" descriz="67578"/>
<marker lat="50.10721" long="8.68774" descriz="162313"/>
<marker lat="50.10668" long="8.69213" descriz="164900"/>
<marker lat="50.11555" long="8.67959" descriz="156077"/>
<marker lat="50.10771" long="8.68509" descriz="169510"/>
<marker lat="50.11648" long="8.67984" descriz="110711"/>
<marker lat="50.1171" long="8.6801" descriz="166904"/>
<marker lat="50.11668" long="8.67984" descriz="111494"/>
<marker lat="50.11248" long="8.67953" descriz="186246"/>
<marker lat="50.10909" long="8.6822" descriz="197277"/>
<marker lat="50.11707" long="8.67986" descriz="99647"/>
<marker lat="50.10664" long="8.69516" descriz="154480"/>
<marker lat="50.10664" long="8.69516" descriz="37169"/>
<marker lat="50.1067" long="8.68738" descriz="82032"/>
<marker lat="50.1067" long="8.68738" descriz="157504"/>
<marker lat="50.1132" long="8.67896" descriz="198074"/>
<marker lat="50.11173" long="8.67932" descriz="68256"/>
<marker lat="50.11701" long="8.67937" descriz="7164"/>
<marker lat="50.10884" long="8.68186" descriz="91474"/>
<marker lat="50.11745" long="8.67948" descriz="149360"/>
<marker lat="50.11117" long="8.67943" descriz="65362"/>
<marker lat="50.11693" long="8.67905" descriz="153694"/>
<marker lat="50.1105" long="8.6797" descriz="4132"/>
<marker lat="50.10564" long="8.69216" descriz="33266"/>
<marker lat="50.11117" long="8.70425" descriz="55841"/>
<marker lat="50.11783" long="8.67894" descriz="116898"/>
<marker lat="50.12035" long="8.68147" descriz="146152"/>
<marker lat="50.10553" long="8.68932" descriz="161976"/>
<marker lat="50.1167" long="8.67809" descriz="199087"/>
<marker lat="50.10716" long="8.6831" descriz="36949"/>
<marker lat="50.1074" long="8.68239" descriz="188082"/>
<marker lat="50.1074" long="8.68239" descriz="164990"/>
<marker lat="50.10531" long="8.68742" descriz="121740"/>
<marker lat="50.10514" long="8.69484" descriz="58543"/>
<marker lat="50.11527" long="8.67684" descriz="50221"/>
<marker lat="50.11074" long="8.67784" descriz="69767"/>
<marker lat="50.11201" long="8.67708" descriz="113822"/>
<marker lat="50.11201" long="8.67708" descriz="180428"/>
<marker lat="50.11922" long="8.6781" descriz="115081"/>
<marker lat="50.10566" long="8.68387" descriz="75250"/>
<marker lat="50.10566" long="8.68387" descriz="17747"/>
<marker lat="50.10429" long="8.6918" descriz="190141"/>
<marker lat="50.1126" long="8.67607" descriz="190598"/>
<marker lat="50.10519" long="8.68484" descriz="48352"/>
<marker lat="50.1069" long="8.68023" descriz="111123"/>
<marker lat="50.11976" long="8.6777" descriz="81980"/>
<marker lat="50.12241" long="8.68107" descriz="163409"/>
<marker lat="50.12448" long="8.68639" descriz="173589"/>
<marker lat="50.12448" long="8.68639" descriz="85529"/>
<marker lat="50.10353" long="8.69028" descriz="132335"/>
<marker lat="50.10404" long="8.68606" descriz="85737"/>
<marker lat="50.10448" long="8.68321" descriz="135783"/>
<marker lat="50.11573" long="8.67417" descriz="84787"/>
<marker lat="50.11412" long="8.67369" descriz="73353"/>
<marker lat="50.11305" long="8.67349" descriz="162343"/>
<marker lat="50.10943" long="8.6746" descriz="96385"/>
<marker lat="50.10943" long="8.6746" descriz="15505"/>
<marker lat="50.11202" long="8.67322" descriz="120263"/>
<marker lat="50.1209" long="8.67568" descriz="112097"/>
<marker lat="50.10754" long="8.67575" descriz="119293"/>
<marker lat="50.10754" long="8.67575" descriz="156263"/>
<marker lat="50.10542" long="8.67777" descriz="105162"/>
<marker lat="50.10542" long="8.67777" descriz="124352"/>
<marker lat="50.10542" long="8.67777" descriz="168228"/>
<marker lat="50.11339" long="8.67182" descriz="133210"/>
<marker lat="50.11375" long="8.67014" descriz="193572"/>
<marker lat="50.10472" long="8.6761" descriz="50912"/>
<marker lat="50.11049" long="8.67083" descriz="121685"/>
<marker lat="50.11537" long="8.66966" descriz="64466"/>
<marker lat="50.1017" long="8.68062" descriz="177834"/>
<marker lat="50.11431" long="8.6915" descriz="111130"/>
<marker lat="50.11007" long="8.68744" descriz="45762"/>
<marker lat="50.12234" long="8.70207" descriz="2784"/>
<marker lat="50.11139" long="8.68805" descriz="6860"/>
<marker lat="50.11339" long="8.6956" descriz="118167"/>
<marker lat="50.12889" long="8.693" descriz="97772"/>
<marker lat="50.10807" long="8.65514" descriz="8886"/>
<marker lat="50.11666" long="8.65286" descriz="1025"/>
<marker lat="50.09777" long="8.67079" descriz="483"/>
<marker lat="50.1096" long="8.66068" descriz="105024"/>
<marker lat="50.13123" long="8.71454" descriz="165171"/>
<marker lat="50.0948" long="8.69094" descriz="26166"/>
<marker lat="50.12472" long="8.70594" descriz="192115"/>
<marker lat="50.12837" long="8.69195" descriz="132270"/>
<marker lat="50.09992" long="8.69138" descriz="70070"/>
<marker lat="50.0975" long="8.69101" descriz="171279"/>
<marker lat="50.10978" long="8.71679" descriz="113892"/>
<marker lat="50.10781" long="8.66483" descriz="58574"/>
<marker lat="50.12587" long="8.71548" descriz="195988"/>
<marker lat="50.10498" long="8.71803" descriz="40397"/>
<marker lat="50.0948" long="8.69094" descriz="38946"/>
<marker lat="50.13497" long="8.68407" descriz="84626"/>
<marker lat="50.13735" long="8.69473" descriz="56299"/>
<marker lat="50.13735" long="8.69473" descriz="110527"/>
<marker lat="50.0881" long="8.69223" descriz="123894"/>
<marker lat="50.12924" long="8.68367" descriz="22183"/>
<marker lat="50.08672" long="8.68539" descriz="95562"/>
<marker lat="50.12347" long="8.63397" descriz="56478"/>
<marker lat="50.12485" long="8.74558" descriz="877"/>
<marker lat="50.1235" long="8.63629" descriz="1364"/>
<marker lat="50.0857" long="8.69158" descriz="7477"/>
<marker lat="50.11742" long="8.64302" descriz="171619"/>
<marker lat="50.14898" long="8.71308" descriz="99524"/>
<marker lat="50.12293" long="8.74555" descriz="24530"/>
<marker lat="50.09422" long="8.72738" descriz="132428"/>
<marker lat="50.10737" long="8.74308" descriz="88826"/>
<marker lat="50.15418" long="8.68651" descriz="167383"/>
<marker lat="50.10053" long="8.74679" descriz="95788"/>
<marker lat="50.10053" long="8.74679" descriz="24963"/>
<marker lat="50.12407" long="8.61248" descriz="72002"/>
<marker lat="50.09702" long="8.75474" descriz="69825"/>
<marker lat="50.15655" long="8.73367" descriz="107987"/>
<marker lat="50.11963" long="8.75563" descriz="76216"/>
<marker lat="50.11062" long="8.7565" descriz="182285"/>
<marker lat="50.11915" long="8.75661" descriz="30085"/>
<marker lat="50.10922" long="8.75879" descriz="19036"/>
<marker lat="50.1189" long="8.62358" descriz="95860"/>
<marker lat="50.1147" long="8.7621" descriz="128515"/>
<marker lat="50.13292" long="8.75623" descriz="21703"/>
<marker lat="50.08171" long="8.74358" descriz="176512"/>
<marker lat="50.16285" long="8.69238" descriz="183421"/>
<marker lat="50.11775" long="8.61596" descriz="74353"/>
<marker lat="50.13159" long="8.76409" descriz="46546"/>
<marker lat="50.1242" long="8.76939" descriz="47491"/>
<marker lat="50.1066" long="8.60958" descriz="103334"/>
<marker lat="50.10664" long="8.75822" descriz="189424"/>
<marker lat="50.10795" long="8.76529" descriz="61750"/>
<marker lat="50.1345" long="8.76537" descriz="78635"/>
<marker lat="50.06622" long="8.61888" descriz="131310"/>
<marker lat="50.08685" long="8.59951" descriz="185029"/>
<marker lat="50.04746" long="8.69526" descriz="57512"/>
<marker lat="50.08539" long="8.77172" descriz="178255"/>
<marker lat="50.0698" long="8.7659" descriz="166289"/>
<marker lat="50.12272" long="8.6031" descriz="92266"/>
<marker lat="50.14114" long="8.59722" descriz="99195"/>
<marker lat="50.04746" long="8.69526" descriz="157821"/>
<marker lat="50.10557" long="8.78477" descriz="188139"/>
<marker lat="50.06182" long="8.62011" descriz="183587"/>
<marker lat="50.17964" long="8.66473" descriz="124580"/>
<marker lat="50.0929" long="8.80019" descriz="173514"/>
<marker lat="50.18942" long="8.66664" descriz="184540"/>
<marker lat="50.0449" long="8.751" descriz="194660"/>
<marker lat="50.16613" long="8.77304" descriz="11862"/>
<marker lat="50.05125" long="8.75115" descriz="162871"/>
<marker lat="50.05291" long="8.75732" descriz="79544"/>
<marker lat="50.05004" long="8.75582" descriz="99785"/>
<marker lat="50.19311" long="8.74289" descriz="65402"/>
<marker lat="50.07416" long="8.57205" descriz="41934"/>
<marker lat="50.08558" long="8.56264" descriz="89528"/>
<marker lat="50.19311" long="8.74289" descriz="87540"/>
<marker lat="50.01068" long="8.69038" descriz="3929"/>
<marker lat="50.20266" long="8.74404" descriz="5352"/>
<marker lat="50.05236" long="8.57168" descriz="79887"/>
<marker lat="50.21175" long="8.65576" descriz="175000"/>
<marker lat="50.22129" long="8.63783" descriz="103054"/>
<marker lat="49.99677" long="8.68033" descriz="50427"/>
</markers>
