<markers>
<marker lat="50.17488" long="8.75927" descriz="96592"/>
<marker lat="50.17435" long="8.7573" descriz="96592"/>
<marker lat="50.15165" long="8.77683" descriz="96592"/>
<marker lat="50.17111" long="8.77186" descriz="155999" real_lat="50.17111" real_lon="8.77186" distance="9.493073054631141E-5"/>
<marker lat="50.17231" long="8.7793" descriz="11862" real_lat="50.17231" real_lon="8.7793" distance="0.0"/>
<marker lat="50.15986" long="8.73999" descriz="78635" real_lat="50.15986" real_lon="8.73999" distance="0.0"/>
<marker lat="50.14865" long="8.76853" descriz="158937" real_lat="50.14865" real_lon="8.76853" distance="0.0"/>
<marker lat="50.17809" long="8.73553" descriz="182285" real_lat="50.17814" real_lon="8.73532" distance="0.01595344749605581"/>
<marker lat="50.16558" long="8.72966" descriz="87540" real_lat="50.16825" real_lon="8.73007" distance="0.29830886615066793"/>
<marker lat="50.14301" long="8.75517" descriz="152189" real_lat="50.14296" real_lon="8.75524" distance="0.007469425931109931"/>
<marker lat="50.14698" long="8.73093" descriz="104129" real_lat="50.14393" real_lon="8.72635" distance="0.4706488700129117"/>
<marker lat="50.14296" long="8.75524" descriz="192730" real_lat="50.14296" real_lon="8.75524" distance="9.493073054631141E-5"/>
<marker lat="50.15002" long="8.80616" descriz="94987" real_lat="50.15002" real_lon="8.80616" distance="0.0"/>
<marker lat="50.19625" long="8.70576" descriz="174544" real_lat="50.19625" real_lon="8.70576" distance="0.0"/>
<marker lat="50.15286" long="8.80313" descriz="184305" real_lat="50.15147" real_lon="8.80241" distance="0.16284375570365034"/>
<marker lat="50.14296" long="8.75524" descriz="73517" real_lat="50.14296" real_lon="8.75524" distance="9.493073054631141E-5"/>
<marker lat="50.14414" long="8.70481" descriz="155351" real_lat="50.14414" real_lon="8.70481" distance="0.0"/>
<marker lat="50.15404" long="8.81856" descriz="90490" real_lat="50.15404" real_lon="8.81856" distance="0.0"/>
<marker lat="50.14131" long="8.70003" descriz="43860" real_lat="50.14065" real_lon="8.69954" distance="0.08126902245152368"/>
<marker lat="50.15636" long="8.6888" descriz="116637" real_lat="50.15636" real_lon="8.6888" distance="0.0"/>
<marker lat="50.13741" long="8.80294" descriz="46546" real_lat="50.13726" real_lon="8.80253" distance="0.03364460805492804"/>
<marker lat="50.14359" long="8.70455" descriz="85822" real_lat="50.14359" real_lon="8.70455" distance="0.0"/>
<marker lat="50.1361" long="8.80805" descriz="28469" real_lat="50.1361" real_lon="8.80805" distance="0.0"/>
<marker lat="50.12586" long="8.74855" descriz="103452" real_lat="50.12586" real_lon="8.74855" distance="0.0"/>
<marker lat="50.17037" long="8.67812" descriz="157306" real_lat="50.17037" real_lon="8.67812" distance="0.0"/>
<marker lat="50.14648" long="8.70654" descriz="185164" real_lat="50.15266" real_lon="8.71343" distance="0.8444900883358728"/>
<marker lat="50.13211" long="8.7653" descriz="152724" real_lat="50.13211" real_lon="8.7653" distance="0.0"/>
<marker lat="50.12681" long="8.72008" descriz="138110" real_lat="50.12681" real_lon="8.72008" distance="0.0"/>
<marker lat="50.11561" long="8.76959" descriz="176512" real_lat="50.11561" real_lon="8.76959" distance="0.0"/>
<marker lat="50.1277" long="8.70969" descriz="113152" real_lat="50.1277" real_lon="8.70969" distance="9.493073054631141E-5"/>
<marker lat="50.17964" long="8.66473" descriz="177596" real_lat="50.17964" real_lon="8.66473" distance="0.0"/>
<marker lat="50.19921" long="8.83948" descriz="196324" real_lat="50.19921" real_lon="8.83948" distance="0.0"/>
<marker lat="50.12" long="8.71796" descriz="4702" real_lat="50.12" real_lon="8.71796" distance="0.0"/>
<marker lat="50.18315" long="8.665" descriz="56299" real_lat="50.18315" real_lon="8.665" distance="0.0"/>
<marker lat="50.12613" long="8.71628" descriz="195988" real_lat="50.12613" real_lon="8.71628" distance="0.0"/>
<marker lat="50.23526" long="8.74599" descriz="4068" real_lat="50.23526" real_lon="8.74599" distance="0.0"/>
<marker lat="50.15315" long="8.67967" descriz="166460" real_lat="50.15315" real_lon="8.67967" distance="0.0"/>
<marker lat="50.12814" long="8.81575" descriz="159760" real_lat="50.12814" real_lon="8.81575" distance="0.0"/>
<marker lat="50.13323" long="8.69552" descriz="146152" real_lat="50.13323" real_lon="8.69552" distance="0.0"/>
<marker lat="50.12842" long="8.69228" descriz="128342" real_lat="50.12842" real_lon="8.69228" distance="0.0"/>
<marker lat="50.13209" long="8.69491" descriz="141272" real_lat="50.13209" real_lon="8.69491" distance="NaN"/>
<marker lat="50.14728" long="8.6712" descriz="62590" real_lat="50.14728" real_lon="8.6712" distance="0.0"/>
<marker lat="50.11671" long="8.72751" descriz="37467" real_lat="50.11671" real_lon="8.72751" distance="0.0"/>
<marker lat="50.1132" long="8.67896" descriz="163409" real_lat="50.1132" real_lon="8.67896" distance="9.493073054631141E-5"/>
<marker lat="50.10441" long="8.7645" descriz="14477" real_lat="50.10441" real_lon="8.7645" distance="0.0"/>
<marker lat="50.14046" long="8.64982" descriz="25056" real_lat="50.14046" real_lon="8.64742" distance="0.17102937612665703"/>
<marker lat="50.10498" long="8.71803" descriz="69894" real_lat="50.10498" real_lon="8.71803" distance="0.0"/>
<marker lat="50.17522" long="8.63296" descriz="78225" real_lat="50.17522" real_lon="8.63296" distance="0.0"/>
<marker lat="50.11561" long="8.68933" descriz="121692" real_lat="50.11561" real_lon="8.68933" distance="0.0"/>
<marker lat="50.11998" long="8.68617" descriz="101464" real_lat="50.11998" real_lon="8.68617" distance="0.0"/>
<marker lat="50.10664" long="8.69516" descriz="154480" real_lat="50.10664" real_lon="8.69516" distance="9.493073054631141E-5"/>
<marker lat="50.11168" long="8.79918" descriz="188139" real_lat="50.11168" real_lon="8.79918" distance="0.0"/>
<marker lat="50.12003" long="8.68675" descriz="189424" real_lat="50.12003" real_lon="8.68675" distance="0.0"/>
<marker lat="50.10038" long="8.73675" descriz="47068" real_lat="50.10047" real_lon="8.73776" distance="0.07272685335969077"/>
<marker lat="50.11457" long="8.68626" descriz="181830" real_lat="50.11457" real_lon="8.68626" distance="0.0"/>
<marker lat="50.10657" long="8.72656" descriz="173514" real_lat="50.10657" real_lon="8.72656" distance="9.493073054631141E-5"/>
<marker lat="50.11527" long="8.67684" descriz="50221" real_lat="50.11527" real_lon="8.67684" distance="NaN"/>
<marker lat="50.11502" long="8.69331" descriz="69825" real_lat="50.11502" real_lon="8.69331" distance="0.0"/>
<marker lat="50.1036" long="8.77216" descriz="115030" real_lat="50.1036" real_lon="8.77216" distance="0.0"/>
<marker lat="50.11502" long="8.69331" descriz="67174" real_lat="50.11502" real_lon="8.69331" distance="0.0"/>
<marker lat="50.10708" long="8.73542" descriz="61750" real_lat="50.10697" real_lon="8.73953" distance="0.2933476315110398"/>
<marker lat="50.11098" long="8.68481" descriz="42921" real_lat="50.11098" real_lon="8.68481" distance="1.3425232662457948E-4"/>
<marker lat="50.12035" long="8.68147" descriz="39989" real_lat="50.12035" real_lon="8.68147" distance="0.0"/>
<marker lat="50.11362" long="8.6873" descriz="72002" real_lat="50.11376" real_lon="8.68708" distance="0.022099295018772235"/>
<marker lat="50.16703" long="8.64467" descriz="78310" real_lat="50.16703" real_lon="8.64467" distance="0.0"/>
<marker lat="50.10929" long="8.6943" descriz="166289" real_lat="50.10929" real_lon="8.6943" distance="0.0"/>
<marker lat="50.1095" long="8.69363" descriz="104487" real_lat="50.1095" real_lon="8.69363" distance="0.0"/>
<marker lat="50.11707" long="8.67986" descriz="69456" real_lat="50.11668" real_lon="8.67984" distance="0.04338739432546774"/>
<marker lat="50.16211" long="8.64601" descriz="110711" real_lat="50.16211" real_lon="8.64601" distance="0.0"/>
<marker lat="50.09863" long="8.75113" descriz="24963" real_lat="50.09863" real_lon="8.75113" distance="9.493073054631141E-5"/>
<marker lat="50.10689" long="8.69205" descriz="162313" real_lat="50.10689" real_lon="8.69205" distance="0.0"/>
<marker lat="50.10498" long="8.71803" descriz="171118" real_lat="50.10563" real_lon="8.70598" distance="0.8623749490986052"/>
<marker lat="50.1148" long="8.68484" descriz="124103" real_lat="50.1148" real_lon="8.68484" distance="0.0"/>
<marker lat="50.10712" long="8.68773" descriz="103187" real_lat="50.10435" real_lon="8.6823" distance="0.49478465042893727"/>
<marker lat="50.10721" long="8.68774" descriz="185029" real_lat="50.10721" real_lon="8.68774" distance="0.0"/>
<marker lat="50.10721" long="8.68786" descriz="27351" real_lat="50.10721" real_lon="8.68786" distance="0.0"/>
<marker lat="50.1142" long="8.67124" descriz="21843" real_lat="50.1142" real_lon="8.67124" distance="NaN"/>
<marker lat="50.09628" long="8.70631" descriz="3356" real_lat="50.09628" real_lon="8.70631" distance="0.0"/>
<marker lat="50.10915" long="8.67501" descriz="99647" real_lat="50.10915" real_lon="8.67501" distance="0.0"/>
<marker lat="50.10405" long="8.69021" descriz="92068" real_lat="50.10405" real_lon="8.69021" distance="0.0"/>
<marker lat="50.11666" long="8.65286" descriz="160974" real_lat="50.11666" real_lon="8.65286" distance="0.0"/>
<marker lat="50.11293" long="8.67136" descriz="116898" real_lat="50.11293" real_lon="8.67136" distance="0.0"/>
<marker lat="50.0948" long="8.69094" descriz="73286" real_lat="50.0948" real_lon="8.69094" distance="0.0"/>
<marker lat="50.11375" long="8.67014" descriz="193415" real_lat="50.11375" real_lon="8.67014" distance="0.0"/>
<marker lat="50.11563" long="8.66987" descriz="141615" real_lat="50.11563" real_lon="8.66987" distance="0.0"/>
<marker lat="50.10882" long="8.67744" descriz="198074" real_lat="50.10882" real_lon="8.67744" distance="0.0"/>
<marker lat="50.10911" long="8.67484" descriz="9322" real_lat="50.10911" real_lon="8.67484" distance="9.493073054631141E-5"/>
<marker lat="50.1054" long="8.68953" descriz="179904" real_lat="50.1054" real_lon="8.68953" distance="0.0"/>
<marker lat="50.10792" long="8.65316" descriz="110657" real_lat="50.10792" real_lon="8.65316" distance="0.0"/>
<marker lat="50.08896" long="8.69109" descriz="111494" real_lat="50.08896" real_lon="8.69109" distance="0.0"/>
<marker lat="50.09531" long="8.65725" descriz="195384" real_lat="50.0946" real_lon="8.65342" distance="0.2843715910890007"/>
<marker lat="50.08678" long="8.69156" descriz="181416" real_lat="50.08678" real_lon="8.69156" distance="0.0"/>
<marker lat="50.08808" long="8.65963" descriz="29151" real_lat="50.08848" real_lon="8.65146" distance="0.5845419380001567"/>
<marker lat="51.08907" long="10.11485" descriz="19488" real_lat="51.08908" real_lon="10.1142" distance="0.04540924943880103"/>
<marker lat="50.86784" long="9.76227" descriz="71078" real_lat="50.8679" real_lon="9.76132" distance="0.06699729162466805"/>
<marker lat="50.91915" long="8.2453" descriz="101618" real_lat="50.91884" real_lon="8.24612" distance="0.06702163361501136"/>
<marker lat="50.83898" long="10.07533" descriz="149257" real_lat="50.83893" real_lon="10.07389" distance="0.10126443954597215"/>
<marker lat="50.1137" long="8.61839" descriz="171619" real_lat="50.1137" real_lon="8.61839" distance="0.0"/>
<marker lat="50.08673" long="8.65926" descriz="147869" real_lat="50.08673" real_lon="8.65926" distance="0.0"/>
<marker lat="50.10241" long="8.55782" descriz="47909" real_lat="50.10241" real_lon="8.55782" distance="0.0"/>
<marker lat="50.03637" long="8.69543" descriz="125662" real_lat="50.03637" real_lon="8.69543" distance="0.0"/>
<marker lat="50.03368" long="8.69587" descriz="115081" real_lat="50.02834" real_lon="8.69569" distance="0.5938915214589908"/>
<marker lat="50.05973" long="8.69512" descriz="190119" real_lat="50.04746" real_lon="8.69526" distance="1.3643327178241589"/>
<marker lat="50.04072" long="8.69535" descriz="24951" real_lat="50.04072" real_lon="8.69535" distance="NaN"/>
<marker lat="50.0032" long="8.68265" descriz="19036" real_lat="50.0032" real_lon="8.68265" distance="0.0"/>
<marker lat="50.04475" long="8.69523" descriz="20750" real_lat="50.04475" real_lon="8.69523" distance="0.0"/>
</markers>
