<markers>
<marker lat="48.79153" long="9.69719" descriz="179004"/>
<marker lat="48.77772" long="9.68793" descriz="179004"/>
<marker lat="49.26339" long="9.99573" descriz="179004"/>
<marker lat="48.7831" long="9.6383" descriz="108798" real_lat="48.7831" real_lon="9.6383" distance="0.0"/>
<marker lat="48.70181" long="9.66761" descriz="66732" real_lat="48.70181" real_lon="9.66761" distance="0.0"/>
<marker lat="50.0857" long="8.69158" descriz="154169" real_lat="50.0857" real_lon="8.69158" distance="9.493073054631141E-5"/>
<marker lat="50.15213" long="8.7126" descriz="185164" real_lat="50.15266" real_lon="8.71343" distance="0.08348352231707575"/>
<marker lat="50.08052" long="8.73144" descriz="75250" real_lat="50.08089" real_lon="8.73133" distance="0.041882207556099345"/>
<marker lat="50.04814" long="8.95201" descriz="77224" real_lat="50.04814" real_lon="8.95201" distance="9.493073054631141E-5"/>
<marker lat="50.04172" long="8.74762" descriz="79544" real_lat="50.04172" real_lon="8.74762" distance="0.0"/>
<marker lat="50.085" long="8.69167" descriz="60529" real_lat="50.085" real_lon="8.69167" distance="0.0"/>
<marker lat="50.01068" long="8.69038" descriz="119759" real_lat="50.01068" real_lon="8.69038" distance="9.493073054631141E-5"/>
<marker lat="50.10454" long="8.69536" descriz="9644" real_lat="50.10454" real_lon="8.69536" distance="0.0"/>
<marker lat="49.48281" long="7.88708" descriz="99942" real_lat="49.48408" real_lon="7.89144" distance="0.3451580843659617"/>
<marker lat="50.05389" long="8.73031" descriz="55435" real_lat="50.05389" real_lon="8.73031" distance="9.493073054631141E-5"/>
<marker lat="50.02718" long="8.72085" descriz="121795" real_lat="50.02718" real_lon="8.72085" distance="0.0"/>
<marker lat="50.045" long="8.69524" descriz="17747" real_lat="50.04746" real_lon="8.69526" distance="0.2735300801054189"/>
<marker lat="50.1488" long="8.69193" descriz="191484" real_lat="50.1488" real_lon="8.69193" distance="0.0"/>
<marker lat="50.0557" long="8.69716" descriz="141907" real_lat="50.0557" real_lon="8.69716" distance="0.0"/>
<marker lat="50.04041" long="8.6953" descriz="50427" real_lat="50.04475" real_lon="8.69523" distance="0.48258865782486543"/>
<marker lat="50.0868" long="8.95891" descriz="190880" real_lat="50.08691" real_lon="8.95868" distance="0.020465445102648826"/>
<marker lat="49.52693" long="7.9302" descriz="152099" real_lat="49.52693" real_lon="7.9302" distance="0.0"/>
<marker lat="50.0962" long="9.02338" descriz="125525" real_lat="50.0962" real_lon="9.02338" distance="0.0"/>
<marker lat="49.48618" long="7.89784" descriz="156966" real_lat="49.48618" real_lon="7.89784" distance="0.0"/>
<marker lat="48.69198" long="7.63501" descriz="45350" real_lat="48.69198" real_lon="7.63501" distance="0.0"/>
</markers>
