<markers>
<marker lat="50.09445" long="8.68137" descriz="119293"/>
<marker lat="50.10842" long="8.67699" descriz="119293"/>
<marker lat="50.05244" long="8.72128" descriz="119293"/>
<marker lat="50.09445" long="8.68137" descriz="184962" real_lat="50.09604" real_lon="8.68052" distance="0.1868989848690608"/>
<marker lat="50.10328" long="8.67936" descriz="165072" real_lat="50.18613" real_lon="8.69221" distance="9.25744984606886"/>
<marker lat="50.09985" long="8.69131" descriz="181852" real_lat="50.10405" real_lon="8.69021" distance="0.47353998602941727"/>
<marker lat="50.10645" long="8.68732" descriz="179904" real_lat="50.1054" real_lon="8.68953" distance="0.19613548159995095"/>
<marker lat="50.09628" long="8.66909" descriz="105162" real_lat="50.09628" real_lon="8.66909" distance="0.0"/>
<marker lat="50.10222" long="8.68045" descriz="168228" real_lat="50.04475" real_lon="8.69523" distance="6.476525733875219"/>
<marker lat="50.10448" long="8.68321" descriz="135783" real_lat="50.11498" real_lon="8.67282" distance="1.3827338008965484"/>
<marker lat="50.10464" long="8.68523" descriz="132335" real_lat="50.1138" real_lon="8.65054" distance="2.675170175951285"/>
<marker lat="50.10552" long="8.68406" descriz="20487" real_lat="50.09856" real_lon="8.66719" distance="1.4305531529871913"/>
<marker lat="50.10696" long="8.68041" descriz="105190" real_lat="50.1507" real_lon="8.9089" distance="16.997304961455384"/>
<marker lat="50.10569" long="8.68587" descriz="186897" real_lat="50.11423" real_lon="8.68797" distance="0.9612940123232787"/>
<marker lat="50.1074" long="8.68239" descriz="156280" real_lat="50.08161" real_lon="8.54406" distance="10.27541306044642"/>
<marker lat="50.10645" long="8.68732" descriz="24951" real_lat="50.04072" real_lon="8.69535" distance="7.330921404195411"/>
<marker lat="50.1066" long="8.67358" descriz="176671" real_lat="50.10572" real_lon="8.67255" distance="0.12234910319462047"/>
<marker lat="50.10771" long="8.68509" descriz="106890" real_lat="50.10771" real_lon="8.68509" distance="9.493073054631141E-5"/>
<marker lat="50.10771" long="8.68509" descriz="169510" real_lat="50.10771" real_lon="8.68509" distance="9.493073054631141E-5"/>
<marker lat="50.10403" long="8.69009" descriz="65362" real_lat="50.05571" real_lon="8.69684" distance="5.394224770988915"/>
<marker lat="50.10405" long="8.69021" descriz="191484" real_lat="50.1488" real_lon="8.69193" distance="4.97724391943955"/>
<marker lat="50.10405" long="8.69021" descriz="181416" real_lat="50.08678" real_lon="8.69156" distance="1.9226569235599937"/>
<marker lat="50.10553" long="8.68932" descriz="111494" real_lat="50.08896" real_lon="8.69109" distance="1.8467316932567979"/>
<marker lat="50.10721" long="8.68774" descriz="27351" real_lat="50.10721" real_lon="8.68786" distance="0.008557466979797304"/>
<marker lat="50.10721" long="8.68774" descriz="92068" real_lat="50.10405" real_lon="8.69021" distance="0.39304016650117335"/>
<marker lat="50.10721" long="8.68774" descriz="162313" real_lat="50.10689" real_lon="8.69205" distance="0.30940741713979125"/>
<marker lat="50.10016" long="8.66795" descriz="59925" real_lat="50.09871" real_lon="8.66544" distance="0.24091949401667462"/>
<marker lat="50.10564" long="8.69216" descriz="85737" real_lat="50.10404" real_lon="8.68606" distance="0.4699946074503872"/>
<marker lat="50.10403" long="8.68141" descriz="157504" real_lat="50.10418" real_lon="8.68195" distance="0.04196732883928956"/>
<marker lat="50.10222" long="8.68045" descriz="124352" real_lat="50.10222" real_lon="8.68045" distance="0.0"/>
<marker lat="50.0948" long="8.69094" descriz="73286" real_lat="50.0948" real_lon="8.69094" distance="0.0"/>
<marker lat="50.09827" long="8.67148" descriz="138860" real_lat="50.10106" real_lon="8.67457" distance="0.38053475638970835"/>
<marker lat="50.10542" long="8.67777" descriz="156263" real_lat="50.10542" real_lon="8.67777" distance="0.0"/>
<marker lat="50.0857" long="8.69158" descriz="154169" real_lat="50.0857" real_lon="8.69158" distance="9.493073054631141E-5"/>
<marker lat="50.10519" long="8.68484" descriz="103187" real_lat="50.10435" real_lon="8.6823" distance="0.20380268176439326"/>
<marker lat="50.10746" long="8.68777" descriz="190307" real_lat="50.13639" real_lon="8.67146" distance="3.4204109070972297"/>
<marker lat="50.10754" long="8.67575" descriz="69767" real_lat="50.10542" real_lon="8.67777" distance="0.2762531071637854"/>
<marker lat="50.10307" long="8.69789" descriz="9644" real_lat="50.10454" real_lon="8.69536" distance="0.24345644285464224"/>
<marker lat="50.10514" long="8.69484" descriz="178255" real_lat="50.09893" real_lon="8.70689" distance="1.102424889814716"/>
<marker lat="50.10689" long="8.69205" descriz="139214" real_lat="50.147" real_lon="8.90033" distance="15.50206883559881"/>
<marker lat="50.10882" long="8.67744" descriz="198074" real_lat="50.10882" real_lon="8.67744" distance="0.0"/>
<marker lat="50.10909" long="8.68349" descriz="74999" real_lat="50.12472" real_lon="8.70594" distance="2.3626835879930432"/>
<marker lat="50.10911" long="8.67484" descriz="9322" real_lat="50.10911" real_lon="8.67484" distance="9.493073054631141E-5"/>
<marker lat="50.10915" long="8.67501" descriz="99647" real_lat="50.10915" real_lon="8.67501" distance="0.0"/>
<marker lat="50.10853" long="8.67256" descriz="96908" real_lat="50.12551" real_lon="8.70695" distance="3.0945760886625413"/>
<marker lat="50.10878" long="8.68059" descriz="197277" real_lat="50.10973" real_lon="8.68199" distance="0.14534158368802128"/>
<marker lat="50.10827" long="8.67154" descriz="101348" real_lat="50.10725" real_lon="8.66762" distance="0.30166972783164786"/>
<marker lat="50.11022" long="8.68132" descriz="172125" real_lat="50.11022" real_lon="8.68132" distance="0.0"/>
<marker lat="50.10936" long="8.68795" descriz="120209" real_lat="50.10936" real_lon="8.68795" distance="0.0"/>
<marker lat="50.10971" long="8.67305" descriz="56717" real_lat="50.11189" real_lon="8.67695" distance="0.3689056558462796"/>
<marker lat="50.10947" long="8.68772" descriz="69642" real_lat="50.14558" real_lon="8.72788" distance="4.931077692171823"/>
<marker lat="50.10664" long="8.69516" descriz="115030" real_lat="50.1036" real_lon="8.77216" distance="5.50163985234117"/>
<marker lat="50.11065" long="8.67553" descriz="8887" real_lat="50.13767" real_lon="8.77666" distance="7.810168626254925"/>
<marker lat="50.11065" long="8.67553" descriz="95655" real_lat="50.11065" real_lon="8.67553" distance="9.493073054631141E-5"/>
<marker lat="50.10996" long="8.68939" descriz="197341" real_lat="50.12889" real_lon="8.693" distance="2.120495453751962"/>
<marker lat="50.1103" long="8.68811" descriz="185029" real_lat="50.10721" real_lon="8.68774" distance="0.34458738496127544"/>
<marker lat="50.11281" long="8.68116" descriz="57516" real_lat="50.1274" real_lon="8.75259" distance="5.344580649449401"/>
<marker lat="50.11417" long="8.68353" descriz="42921" real_lat="50.11098" real_lon="8.68481" distance="0.3662490576318618"/>
<marker lat="50.11417" long="8.68353" descriz="62590" real_lat="50.14728" real_lon="8.6712" distance="3.784931926145534"/>
<marker lat="50.1148" long="8.68484" descriz="124103" real_lat="50.1148" real_lon="8.68484" distance="0.0"/>
<marker lat="50.10927" long="8.69266" descriz="37467" real_lat="50.11671" real_lon="8.72751" distance="2.6189976011602285"/>
<marker lat="50.11261" long="8.68942" descriz="128536" real_lat="50.11479" real_lon="8.69518" distance="0.47689530345277487"/>
<marker lat="50.11527" long="8.67684" descriz="50221" real_lat="50.11527" real_lon="8.67684" distance="NaN"/>
<marker lat="50.11103" long="8.6648" descriz="58574" real_lat="50.11103" real_lon="8.6648" distance="0.0"/>
<marker lat="50.11338" long="8.66865" descriz="197419" real_lat="50.11906" real_lon="8.67527" distance="0.7884436612210454"/>
<marker lat="50.11133" long="8.70457" descriz="103452" real_lat="50.12586" real_lon="8.74855" distance="3.5272885184695624"/>
<marker lat="50.11322" long="8.65196" descriz="50912" real_lat="50.10879" real_lon="8.66189" distance="0.8625473573506546"/>
<marker lat="50.11329" long="8.69315" descriz="93883" real_lat="50.1503" real_lon="8.99961" distance="22.227226760868398"/>
<marker lat="50.11566" long="8.6878" descriz="128342" real_lat="50.12842" real_lon="8.69228" distance="1.4542819688038289"/>
<marker lat="50.11652" long="8.68322" descriz="157306" real_lat="50.17037" real_lon="8.67812" distance="5.998577307522936"/>
<marker lat="50.11736" long="8.69109" descriz="151113" real_lat="50.11736" real_lon="8.69109" distance="0.0"/>
<marker lat="50.11632" long="8.6765" descriz="152724" real_lat="50.13211" real_lon="8.7653" distance="6.569194957914606"/>
<marker lat="50.11745" long="8.67948" descriz="21622" real_lat="50.14805" real_lon="8.68187" distance="3.4066626033006777"/>
<marker lat="50.11783" long="8.67894" descriz="69456" real_lat="50.11668" real_lon="8.67984" distance="0.14306520936493475"/>
<marker lat="50.11454" long="8.67023" descriz="132270" real_lat="50.186" real_lon="8.73549" distance="9.206065134608423"/>
<marker lat="50.1189" long="8.68362" descriz="28469" real_lat="50.1361" real_lon="8.80805" distance="9.073404382305485"/>
<marker lat="50.11982" long="8.68723" descriz="121692" real_lat="50.11561" real_lon="8.68933" distance="0.49146907204294393"/>
<marker lat="50.12035" long="8.68147" descriz="39989" real_lat="50.12035" real_lon="8.68147" distance="0.0"/>
<marker lat="50.12029" long="8.6799" descriz="146152" real_lat="50.13323" real_lon="8.69552" distance="1.8193030696951566"/>
<marker lat="50.08033" long="8.70096" descriz="91474" real_lat="50.08033" real_lon="8.70096" distance="0.0"/>
<marker lat="50.11562" long="8.67374" descriz="116898" real_lat="50.11293" real_lon="8.67136" distance="0.343886384728955"/>
<marker lat="50.08218" long="8.66398" descriz="123894" real_lat="50.08218" real_lon="8.66398" distance="0.0"/>
<marker lat="50.11027" long="8.69992" descriz="33266" real_lat="50.15535" real_lon="8.97267" distance="20.075686489011893"/>
<marker lat="50.11502" long="8.69331" descriz="130694" real_lat="50.11591" real_lon="8.6954" distance="0.17888143940658127"/>
<marker lat="50.11227" long="8.6774" descriz="113822" real_lat="50.11201" real_lon="8.67708" distance="0.03682920857466921"/>
<marker lat="50.1126" long="8.67607" descriz="115878" real_lat="50.1116" real_lon="8.67786" distance="0.16927442991395436"/>
<marker lat="50.1132" long="8.67896" descriz="4132" real_lat="50.1132" real_lon="8.67896" distance="9.493073054631141E-5"/>
<marker lat="50.11305" long="8.67349" descriz="97516" real_lat="50.11305" real_lon="8.67349" distance="0.0"/>
<marker lat="50.11399" long="8.67936" descriz="111123" real_lat="50.11745" real_lon="8.67948" distance="0.3848110693561615"/>
<marker lat="50.11262" long="8.68965" descriz="147921" real_lat="50.11272" real_lon="8.68958" distance="0.012187419999702097"/>
<marker lat="50.11361" long="8.67076" descriz="21843" real_lat="50.1142" real_lon="8.67124" distance="0.07399276516149707"/>
<marker lat="50.11375" long="8.67014" descriz="193415" real_lat="50.11375" real_lon="8.67014" distance="0.0"/>
<marker lat="50.11375" long="8.67014" descriz="73353" real_lat="50.12605" real_lon="8.58863" distance="5.969848933506961"/>
<marker lat="50.11556" long="8.67868" descriz="186246" real_lat="50.11556" real_lon="8.67868" distance="0.0"/>
<marker lat="50.11556" long="8.67868" descriz="146551" real_lat="50.11556" real_lon="8.67868" distance="0.0"/>
<marker lat="50.11306" long="8.69297" descriz="5599" real_lat="50.11354" real_lon="8.69028" distance="0.19909131184573037"/>
<marker lat="50.11505" long="8.67142" descriz="41913" real_lat="50.11425" real_lon="8.67659" distance="0.3792051017583492"/>
<marker lat="50.11547" long="8.69032" descriz="67174" real_lat="50.11502" real_lon="8.69331" distance="0.21897941401850737"/>
<marker lat="50.11701" long="8.67937" descriz="84787" real_lat="50.11701" real_lon="8.67937" distance="0.0"/>
<marker lat="50.1171" long="8.6801" descriz="166904" real_lat="50.1171" real_lon="8.6801" distance="0.0"/>
<marker lat="50.11725" long="8.67533" descriz="141615" real_lat="50.11563" real_lon="8.66987" distance="0.4289409738436676"/>
<marker lat="50.11833" long="8.67673" descriz="5352" real_lat="50.12029" real_lon="8.6799" distance="0.31395973666957877"/>
<marker lat="50.12072" long="8.68" descriz="163409" real_lat="50.1132" real_lon="8.67896" distance="0.839426948758118"/>
<marker lat="50.11619" long="8.65992" descriz="160974" real_lat="50.11666" real_lon="8.65286" distance="0.5060697770014032"/>
<marker lat="50.11619" long="8.65992" descriz="73663" real_lat="50.11538" real_lon="8.66551" distance="0.4086106800072669"/>
<marker lat="50.11125" long="8.65742" descriz="144987" real_lat="50.11125" real_lon="8.65742" distance="0.0"/>
<marker lat="50.11313" long="8.69313" descriz="147891" real_lat="50.11329" real_lon="8.69306" distance="0.01847738333379879"/>
<marker lat="50.11648" long="8.67984" descriz="149360" real_lat="50.11707" real_lon="8.67986" distance="0.06561739547447884"/>
<marker lat="50.11403" long="8.68029" descriz="189178" real_lat="50.11403" real_lon="8.68029" distance="0.0"/>
<marker lat="50.12049" long="8.68624" descriz="101464" real_lat="50.11998" real_lon="8.68617" distance="0.0569258361132958"/>
<marker lat="50.10664" long="8.69516" descriz="154480" real_lat="50.10664" real_lon="8.69516" distance="9.493073054631141E-5"/>
<marker lat="50.11091" long="8.682" descriz="50813" real_lat="50.11167" real_lon="8.68165" distance="0.08811239062544698"/>
<marker lat="50.10953" long="8.6638" descriz="68857" real_lat="50.10887" real_lon="8.66213" distance="0.13988132536146128"/>
<marker lat="50.10787" long="8.6535" descriz="110657" real_lat="50.10792" real_lon="8.65316" distance="0.024874931026267783"/>
<marker lat="50.09628" long="8.70631" descriz="3356" real_lat="50.09628" real_lon="8.70631" distance="0.0"/>
<marker lat="50.10017" long="8.72049" descriz="98901" real_lat="50.10074" real_lon="8.72367" distance="0.23549220475720115"/>
<marker lat="50.11139" long="8.68805" descriz="6860" real_lat="50.11139" real_lon="8.68805" distance="0.0"/>
<marker lat="50.11457" long="8.68626" descriz="181830" real_lat="50.11457" real_lon="8.68626" distance="0.0"/>
<marker lat="50.09562" long="8.65839" descriz="195384" real_lat="50.0946" real_lon="8.65342" distance="0.3722086377213466"/>
<marker lat="50.0879" long="8.65973" descriz="147869" real_lat="50.08673" real_lon="8.65926" distance="0.13434345302992914"/>
<marker lat="50.11257" long="8.68764" descriz="68256" real_lat="50.11272" real_lon="8.68958" distance="0.1393309880809292"/>
<marker lat="50.08848" long="8.65146" descriz="29151" real_lat="50.08848" real_lon="8.65146" distance="9.493073054631141E-5"/>
<marker lat="50.10563" long="8.70598" descriz="171118" real_lat="50.10563" real_lon="8.70598" distance="0.0"/>
<marker lat="50.11451" long="8.71079" descriz="67578" real_lat="50.11451" real_lon="8.71079" distance="0.0"/>
<marker lat="50.13209" long="8.69491" descriz="141272" real_lat="50.13209" real_lon="8.69491" distance="NaN"/>
<marker lat="50.11851" long="8.64432" descriz="78281" real_lat="50.1138" real_lon="8.65054" distance="0.6862478102085955"/>
<marker lat="50.09844" long="8.63268" descriz="138607" real_lat="50.10298" real_lon="8.64398" distance="0.9509736249484897"/>
<marker lat="50.06788" long="8.694" descriz="60529" real_lat="50.085" real_lon="8.69167" distance="1.91081272588601"/>
<marker lat="50.08828" long="8.63215" descriz="41065" real_lat="50.04843" real_lon="8.43848" distance="14.514981559034695"/>
<marker lat="50.11373" long="8.62778" descriz="79714" real_lat="50.11238" real_lon="8.60389" distance="1.710031320032359"/>
<marker lat="50.08808" long="8.63094" descriz="36997" real_lat="50.08931" real_lon="8.6385" distance="0.5563956202534255"/>
<marker lat="50.08801" long="8.62256" descriz="35635" real_lat="50.08784" real_lon="8.62884" distance="0.4484168391555578"/>
<marker lat="50.12165" long="8.63922" descriz="42792" real_lat="50.12314" real_lon="8.63322" distance="0.45869880678709013"/>
<marker lat="50.11792" long="8.73032" descriz="113892" real_lat="50.11671" real_lon="8.72751" distance="0.2413265019655947"/>
<marker lat="50.10527" long="8.72301" descriz="133357" real_lat="50.10527" real_lon="8.72301" distance="0.0"/>
<marker lat="50.05973" long="8.69512" descriz="184157" real_lat="50.05571" real_lon="8.69684" distance="0.46353926276794644"/>
<marker lat="50.11681" long="8.64244" descriz="168986" real_lat="50.11697" real_lon="8.64339" distance="0.07002986652409994"/>
<marker lat="50.12666" long="8.67124" descriz="174796" real_lat="50.13591" real_lon="8.67134" distance="1.0285282793613975"/>
<marker lat="50.10527" long="8.72301" descriz="69894" real_lat="50.10498" real_lon="8.71803" distance="0.3566089035289729"/>
<marker lat="50.10527" long="8.72301" descriz="173514" real_lat="50.10657" real_lon="8.72656" distance="0.29152272157083253"/>
<marker lat="50.10182" long="8.62829" descriz="197862" real_lat="50.08662" real_lon="8.51453" distance="8.28876035220933"/>
<marker lat="50.12587" long="8.71548" descriz="195988" real_lat="50.12613" real_lon="8.71628" distance="0.06393611130643385"/>
<marker lat="50.10038" long="8.73675" descriz="47068" real_lat="50.10047" real_lon="8.73776" distance="0.07272685335969077"/>
<marker lat="50.10708" long="8.73542" descriz="61750" real_lat="50.10697" real_lon="8.73953" distance="0.2933476315110398"/>
<marker lat="50.08931" long="8.6385" descriz="121740" real_lat="50.08828" real_lon="8.63215" distance="0.4672564137952765"/>
<marker lat="50.05973" long="8.69512" descriz="181148" real_lat="50.05973" real_lon="8.69512" distance="0.0"/>
<marker lat="50.12234" long="8.70207" descriz="165171" real_lat="50.12234" real_lon="8.70207" distance="0.0"/>
<marker lat="50.13497" long="8.68407" descriz="178602" real_lat="50.13743" real_lon="8.68478" distance="0.278167402905148"/>
<marker lat="50.12681" long="8.72008" descriz="138110" real_lat="50.12681" real_lon="8.72008" distance="0.0"/>
<marker lat="50.11193" long="8.62047" descriz="114191" real_lat="50.11335" real_lon="8.61528" distance="0.4023406160759238"/>
<marker lat="50.07866" long="8.75229" descriz="75250" real_lat="50.08089" real_lon="8.73133" distance="1.5159660464739473"/>
<marker lat="50.143" long="8.66858" descriz="184600" real_lat="50.12989" real_lon="8.69031" distance="2.126786292188683"/>
<marker lat="50.12126" long="8.6214" descriz="74353" real_lat="50.11894" real_lon="8.61966" distance="0.2862366965942466"/>
<marker lat="50.12407" long="8.61248" descriz="97148" real_lat="50.12184" real_lon="8.61565" distance="0.3354837512318362"/>
<marker lat="50.07659" long="8.61046" descriz="180720" real_lat="50.07664" real_lon="8.60822" distance="0.15993703986980656"/>
<marker lat="50.12926" long="8.62953" descriz="96385" real_lat="50.12926" real_lon="8.62953" distance="0.0"/>
<marker lat="50.14359" long="8.70455" descriz="115722" real_lat="50.14679" real_lon="8.70706" distance="0.39822845179009825"/>
<marker lat="50.09481" long="8.76225" descriz="36949" real_lat="50.09481" real_lon="8.76225" distance="9.493073054631141E-5"/>
<marker lat="50.10053" long="8.74679" descriz="24963" real_lat="50.09863" real_lon="8.75113" distance="0.37476310342496555"/>
<marker lat="50.12407" long="8.61248" descriz="77087" real_lat="50.12388" real_lon="8.60726" distance="0.3727163761770797"/>
<marker lat="50.11389" long="8.62013" descriz="171619" real_lat="50.1137" real_lon="8.61839" distance="0.1258512631133245"/>
<marker lat="50.04746" long="8.69526" descriz="20750" real_lat="50.04475" real_lon="8.69523" distance="0.30133137332643234"/>
<marker lat="50.14359" long="8.70455" descriz="85822" real_lat="50.14359" real_lon="8.70455" distance="0.0"/>
<marker lat="50.13312" long="8.64582" descriz="79536" real_lat="50.13472" real_lon="8.64584" distance="0.17790902843107623"/>
<marker lat="50.09929" long="8.76393" descriz="15454" real_lat="50.09929" real_lon="8.76393" distance="9.493073054631141E-5"/>
<marker lat="50.09611" long="8.757" descriz="126503" real_lat="50.0966" real_lon="8.75486" distance="0.16207372691993954"/>
<marker lat="50.05202" long="8.71357" descriz="117965" real_lat="50.05202" real_lon="8.71357" distance="0.0"/>
<marker lat="50.14248" long="8.70227" descriz="43860" real_lat="50.14065" real_lon="8.69954" distance="0.2815124037077795"/>
<marker lat="50.04746" long="8.69526" descriz="190119" real_lat="50.04746" real_lon="8.69526" distance="0.0"/>
<marker lat="50.14792" long="8.66615" descriz="153694" real_lat="50.14792" real_lon="8.66615" distance="0.0"/>
<marker lat="50.14719" long="8.70713" descriz="155351" real_lat="50.14414" real_lon="8.70481" distance="0.3772737614653967"/>
<marker lat="50.12421" long="8.60859" descriz="147246" real_lat="50.12388" real_lon="8.60726" distance="0.10166380981488232"/>
<marker lat="50.14529" long="8.72755" descriz="113152" real_lat="50.1277" real_lon="8.70969" distance="2.3335371703040657"/>
<marker lat="50.05065" long="8.73474" descriz="55435" real_lat="50.05389" real_lon="8.73031" distance="0.47938709627163045"/>
<marker lat="50.08411" long="8.58826" descriz="147298" real_lat="50.08543" real_lon="8.58918" distance="0.16077869409146536"/>
<marker lat="50.15588" long="8.69467" descriz="116637" real_lat="50.15636" real_lon="8.6888" distance="0.4215645977103169"/>
<marker lat="50.10712" long="8.76775" descriz="14477" real_lat="50.10441" real_lon="8.7645" distance="0.38014927785447233"/>
<marker lat="50.12394" long="8.58825" descriz="100805" real_lat="50.12223" real_lon="8.61413" distance="1.8547085053281411"/>
<marker lat="50.04072" long="8.69535" descriz="125662" real_lat="50.03637" real_lon="8.69543" distance="0.48370839423404627"/>
<marker lat="50.08053" long="8.59485" descriz="88018" real_lat="50.08053" real_lon="8.59485" distance="0.0"/>
<marker lat="50.04041" long="8.6953" descriz="50427" real_lat="50.04475" real_lon="8.69523" distance="0.48258865782486543"/>
<marker lat="50.0376" long="8.71228" descriz="17747" real_lat="50.04746" real_lon="8.69526" distance="1.6367801727371767"/>
<marker lat="50.03486" long="8.69534" descriz="3929" real_lat="50.03368" real_lon="8.69587" distance="0.13655494392744416"/>
<marker lat="50.0898" long="8.57663" descriz="89528" real_lat="50.0898" real_lon="8.57663" distance="NaN"/>
<marker lat="50.11561" long="8.76959" descriz="176512" real_lat="50.11561" real_lon="8.76959" distance="0.0"/>
<marker lat="50.09131" long="8.57973" descriz="185750" real_lat="50.093" real_lon="8.57696" distance="0.2726799928351589"/>
<marker lat="50.15315" long="8.67967" descriz="166460" real_lat="50.15315" real_lon="8.67967" distance="0.0"/>
<marker lat="50.04814" long="8.7547" descriz="79544" real_lat="50.04172" real_lon="8.74762" distance="0.8747215267554375"/>
<marker lat="50.15213" long="8.7126" descriz="185164" real_lat="50.15266" real_lon="8.71343" distance="0.08348352231707575"/>
<marker lat="50.15469" long="8.68513" descriz="22183" real_lat="50.15469" real_lon="8.68513" distance="9.493073054631141E-5"/>
<marker lat="50.02834" long="8.69569" descriz="115081" real_lat="50.02834" real_lon="8.69569" distance="0.0"/>
<marker lat="50.14529" long="8.72755" descriz="104129" real_lat="50.14393" real_lon="8.72635" distance="0.1737191387542186"/>
<marker lat="50.03486" long="8.69534" descriz="169846" real_lat="50.03486" real_lon="8.69534" distance="0.0"/>
<marker lat="50.14498" long="8.75116" descriz="73517" real_lat="50.14296" real_lon="8.75524" distance="0.3673821725640947"/>
<marker lat="50.16023" long="8.6514" descriz="110711" real_lat="50.16211" real_lon="8.64601" distance="0.43715448876047414"/>
<marker lat="50.14865" long="8.76853" descriz="158937" real_lat="50.14865" real_lon="8.76853" distance="0.0"/>
<marker lat="50.07964" long="8.56016" descriz="41934" real_lat="50.08312" real_lon="8.55993" distance="0.3872875624498064"/>
<marker lat="50.16558" long="8.72966" descriz="87540" real_lat="50.16825" real_lon="8.73007" distance="0.29830886615066793"/>
<marker lat="50.09943" long="8.5654" descriz="158278" real_lat="50.1028" real_lon="8.55661" distance="0.7303583103337472"/>
<marker lat="50.02718" long="8.72085" descriz="121795" real_lat="50.02718" real_lon="8.72085" distance="0.0"/>
<marker lat="50.16702" long="8.64417" descriz="78310" real_lat="50.16703" real_lon="8.64467" distance="0.035628756500739274"/>
<marker lat="50.10241" long="8.55782" descriz="47909" real_lat="50.10241" real_lon="8.55782" distance="0.0"/>
<marker lat="50.05902" long="8.59022" descriz="106960" real_lat="50.05828" real_lon="8.58621" distance="0.297840821450634"/>
<marker lat="50.1105" long="8.56496" descriz="6816" real_lat="50.11145" real_lon="8.56425" distance="0.11713602050199359"/>
<marker lat="50.13578" long="8.7718" descriz="86317" real_lat="50.13698" real_lon="8.77452" distance="0.2353309642416113"/>
<marker lat="50.11565" long="8.56784" descriz="95860" real_lat="50.11776" real_lon="8.56715" distance="0.23971240712507924"/>
<marker lat="50.16613" long="8.77304" descriz="11862" real_lat="50.17231" real_lon="8.7793" distance="0.8191122061396389"/>
<marker lat="50.09721" long="8.54221" descriz="181523" real_lat="50.0929" real_lon="8.53182" distance="0.882560817164006"/>
<marker lat="50.10638" long="8.54991" descriz="135187" real_lat="50.10569" real_lon="8.5441" distance="0.4213748436136783"/>
<marker lat="50.01375" long="8.69279" descriz="119759" real_lat="50.01068" real_lon="8.69038" distance="0.3823280459599565"/>
<marker lat="50.17797" long="8.7355" descriz="182285" real_lat="50.17814" real_lon="8.73532" distance="0.02283789526889844"/>
<marker lat="50.0032" long="8.68265" descriz="19036" real_lat="50.0032" real_lon="8.68265" distance="0.0"/>
<marker lat="50.08141" long="8.54462" descriz="24213" real_lat="50.0817" real_lon="8.54428" distance="0.04035147925835912"/>
<marker lat="50.17522" long="8.63296" descriz="78225" real_lat="50.17522" real_lon="8.63296" distance="0.0"/>
<marker lat="50.09721" long="8.54221" descriz="186496" real_lat="50.09721" real_lon="8.54221" distance="0.0"/>
<marker lat="50.18901" long="8.68338" descriz="180428" real_lat="50.1909" real_lon="8.68132" distance="0.25625774850156485"/>
<marker lat="50.15014" long="8.80159" descriz="94987" real_lat="50.15002" real_lon="8.80616" distance="0.3258762921069668"/>
<marker lat="50.17111" long="8.77186" descriz="155999" real_lat="50.17111" real_lon="8.77186" distance="9.493073054631141E-5"/>
<marker lat="50.15345" long="8.80542" descriz="184305" real_lat="50.15147" real_lon="8.80241" distance="0.30733580275317135"/>
<marker lat="49.99964" long="8.72767" descriz="65635" real_lat="49.99786" real_lon="8.73342" distance="0.45614483739145256"/>
<marker lat="50.0657" long="8.84016" descriz="72912" real_lat="50.07283" real_lon="8.85039" distance="1.0777499105109971"/>
<marker lat="50.08302" long="8.51998" descriz="90070" real_lat="50.08302" real_lon="8.51998" distance="0.0"/>
<marker lat="50.08724" long="8.83145" descriz="5662" real_lat="50.08724" real_lon="8.83145" distance="9.493073054631141E-5"/>
<marker lat="49.92057" long="8.64742" descriz="195450" real_lat="49.92057" real_lon="8.64742" distance="0.0"/>
<marker lat="50.04625" long="8.47847" descriz="192075" real_lat="50.04816" real_lon="8.48832" distance="0.7346657286651272"/>
<marker lat="50.01836" long="8.28035" descriz="12441" real_lat="50.0165" real_lon="8.28289" distance="0.27514227454783047"/>
<marker lat="49.75649" long="9.0166" descriz="102640" real_lat="49.75499" real_lon="9.01425" distance="0.23730487737962697"/>
<marker lat="49.68827" long="9.29313" descriz="170990" real_lat="49.69421" real_lon="9.27734" distance="1.3138388712271636"/>
<marker lat="51.6862" long="9.95068" descriz="167873" real_lat="51.68605" real_lon="9.95074" distance="0.017183773376798196"/>
<marker lat="51.55635" long="7.46517" descriz="92330" real_lat="51.54457" real_lon="7.45983" distance="1.3608551664139228"/>
<marker lat="50.79671" long="6.49497" descriz="91758" real_lat="50.79803" real_lon="6.50534" distance="0.7434254926702369"/>
<marker lat="51.23006" long="10.01754" descriz="115171" real_lat="51.22182" real_lon="10.01383" distance="0.9519265909571977"/>
<marker lat="49.85607" long="6.65281" descriz="123830" real_lat="49.85985" real_lon="6.64949" distance="0.482996968735135"/>
<marker lat="50.84902" long="6.97894" descriz="9756" real_lat="50.84465" real_lon="6.97646" distance="0.5161498794894666"/>
<marker lat="49.46459" long="10.42408" descriz="61444" real_lat="49.46697" real_lon="10.41929" distance="0.43570656188770374"/>
<marker lat="51.05344" long="8.9841" descriz="195058" real_lat="51.04191" real_lon="8.97922" distance="1.326622939122561"/>
<marker lat="49.44773" long="9.53783" descriz="124402" real_lat="49.4412" real_lon="9.52421" distance="1.2233939871224504"/>
<marker lat="49.93637" long="9.91574" descriz="138737" real_lat="49.93815" real_lon="9.90559" distance="0.752860462941706"/>
<marker lat="50.87722" long="8.73678" descriz="182200" real_lat="50.87146" real_lon="8.73918" distance="0.662219357877459"/>
<marker lat="49.51869" long="9.44375" descriz="164168" real_lat="49.52414" real_lon="9.43962" distance="0.6753383450077207"/>
<marker lat="49.99123" long="9.85973" descriz="12811" real_lat="49.99421" real_lon="9.84558" distance="1.0643611295631286"/>
<marker lat="49.79564" long="9.76496" descriz="54465" real_lat="49.80016" real_lon="9.75112" distance="1.113219318304177"/>
<marker lat="50.09358" long="9.81627" descriz="179626" real_lat="50.09171" real_lon="9.80733" distance="0.6707614175522462"/>
</markers>
