<markers>
<marker lat="50.1507" long="7.76424" descriz="8269"/>
<marker lat="50.15365" long="7.73272" descriz="8269"/>
<marker lat="49.78116" long="8.92772" descriz="8269"/>
<marker lat="50.11615" long="7.70051" descriz="58760"/>
<marker lat="50.11665" long="7.68368" descriz="70022"/>
<marker lat="50.21085" long="7.69137" descriz="176252"/>
<marker lat="50.20487" long="7.56789" descriz="185187"/>
<marker lat="50.00226" long="7.72531" descriz="137498"/>
<marker lat="50.00031" long="7.73668" descriz="187241"/>
<marker lat="50.15829" long="8.02331" descriz="172627"/>
<marker lat="50.01782" long="7.59236" descriz="63374"/>
<marker lat="50.02757" long="7.54783" descriz="42483"/>
<marker lat="50.26121" long="7.51643" descriz="80761"/>
<marker lat="50.28855" long="7.55081" descriz="129973"/>
<marker lat="49.95324" long="7.75648" descriz="12957"/>
<marker lat="49.95218" long="7.83963" descriz="73472"/>
<marker lat="50.01117" long="8.04906" descriz="62001"/>
<marker lat="50.0231" long="8.10253" descriz="195676"/>
<marker lat="50.12297" long="8.16825" descriz="153054"/>
<marker lat="50.36665" long="8.02739" descriz="67011"/>
<marker lat="49.87146" long="7.8662" descriz="151510"/>
<marker lat="50.42953" long="7.92535" descriz="188675"/>
<marker lat="49.84091" long="7.86406" descriz="170700"/>
<marker lat="49.943" long="8.17507" descriz="304"/>
<marker lat="50.00672" long="8.28883" descriz="125676"/>
<marker lat="50.06723" long="8.37974" descriz="115495"/>
</markers>
