<markers>
<marker lat="50.22144" long="8.99085" descriz="21843"/>
<marker lat="50.33607" long="9.00149" descriz="21843"/>
<marker lat="49.61556" long="9.19974" descriz="21843"/>
<marker lat="50.1507" long="8.9089" descriz="47909" real_lat="50.1507" real_lon="8.9089" distance="0.0"/>
<marker lat="50.29494" long="9.07295" descriz="69642" real_lat="50.29653" real_lon="9.07013" distance="0.267166481361561"/>
<marker lat="50.20365" long="8.83603" descriz="168228" real_lat="50.20365" real_lon="8.83603" distance="0.0"/>
<marker lat="50.33584" long="9.00153" descriz="39894" real_lat="50.33584" real_lon="9.00153" distance="0.0"/>
<marker lat="50.24776" long="9.17399" descriz="120209" real_lat="50.24776" real_lon="9.17399" distance="0.0"/>
<marker lat="50.12492" long="9.08534" descriz="4155" real_lat="50.12492" real_lon="9.08534" distance="0.0"/>
<marker lat="50.33623" long="9.04971" descriz="57516" real_lat="50.33623" real_lon="9.04971" distance="0.0"/>
</markers>
